pyesprima
