Metadata-Version: 1.0
Name: pyesprima
Version: 1.0.0
Summary: Python port of Esprima, the Javascript parser.
Home-page: https://github.com/int3/pyesprima
Author: Jez Ng
Author-email: me@jezng.com
License: BSD
Keywords: javascript parser
Platform: UNKNOWN
Classifier: Topic :: Utilities
Classifier: License :: OSI Approved :: BSD License
